utils/__init__.py
utils/array_utils.py
hj12hj_utils-1.0.0.dist-info/METADATA
hj12hj_utils-1.0.0.dist-info/WHEEL
hj12hj_utils-1.0.0.dist-info/top_level.txt
hj12hj_utils-1.0.0.dist-info/RECORD
