Metadata-Version: 2.1
Name: hj12hj-utils
Version: 1.0.0
Summary: Description of your package
Author: hj
Author-email: your.email@example.com
